{"tempHash":"00F4DC53E3CA8A24","tbluHash":"008A55C1331D3172","rootEntity":"60f39f81d497c1e7","entities":{"15161e5a1310f010":{"parent":"60f39f81d497c1e7","name":"Head_Hispanic_20s_01","factory":"000C4E58A1DA8EC1","blueprint":"0087CB05E0618CD2"},"4305907648559901":{"parent":"60f39f81d497c1e7","name":"Underwear_Boxers","factory":"008736C2691685B1","blueprint":"00692FFA2F8F0EB5"},"4f1031eb0bb4cadf":{"parent":"60f39f81d497c1e7","name":"Body_Full","factory":"008C9419C0263DF3","blueprint":"009E702203139DF5"},"60f39f81d497c1e7":{"parent":null,"name":"OUTFIT_Hippo_Unique_Vallenato_M_Actor_v2","factory":"00A9AD805B92ED71","blueprint":"00B1F416EEE92077","properties":{"m_LocalColliders":{"type":"TArray<SEntityTemplateReference>","value":[]},"m_mTransform":{"type":"SMatrix43","value":{"rotation":{"x":0,"y":0,"z":-1.717010426755565},"position":{"x":-8.657902717590332,"y":8.308995246887207,"z":0}}},"m_vBodypartBoundingMarginMax":{"type":"SVector3","value":{"x":0,"y":0,"z":0.009999999776482582}},"m_eRoomBehaviour":{"type":"ZSpatialEntity.ERoomBehaviour","value":"ROOM_DYNAMIC"},"m_aBodyParts":{"type":"TArray<SEntityTemplateReference>","value":["4f1031eb0bb4cadf","15161e5a1310f010","4305907648559901","881e7302f1ee38c6"],"postInit":true}}},"881e7302f1ee38c6":{"parent":"60f39f81d497c1e7","name":"Hair_Cap","factory":"006594C7AF2B3472","blueprint":"000B3B438FC8C9AC","properties":{"ConstantColorRGB_02_Value":{"type":"SColorRGB","value":"#141414"},"ConstantColorRGB_03_Value":{"type":"SColorRGB","value":"#141414"},"ConstantColorRGB_05_Value":{"type":"SColorRGB","value":"#ffffff"}}}},"propertyOverrides":[],"overrideDeletes":[],"pinConnectionOverrides":[],"pinConnectionOverrideDeletes":[],"externalScenes":[],"subType":"template","quickEntityVersion":3.1,"extraFactoryDependencies":[],"extraBlueprintDependencies":[],"comments":[]}