{
	"tempHash": "0065002A14682B1E",
	"tbluHash": "005619A8B151B340",
	"rootEntity": "4aa97708bd3f57b5",
	"entities": {
		"a6e1d12f7bfb4750": {
			"parent": "4aa97708bd3f57b5",
			"name": "base_male_body",
			"factory": "[assembly:/_pro/characters/assets/_base/pro_male_regular/materials/base_male_body.mi].pc_entitytype",
			"blueprint": "[assembly:/_pro/characters/assets/_base/pro_male_regular/materials/base_male_body.mi].pc_entityblueprint",
			"properties": {
				"m_mTransform": {
					"type": "SMatrix43",
					"value": {
						"rotation": { "x": 0, "y": 0, "z": 0 },
						"position": { "x": 0, "y": 0, "z": 0 }
					}
				},
				"ConstantColorRGB_01_Value_op": {
					"type": "IRenderMaterialEntity.EModifierOperation",
					"value": "eReplace"
				},
				"ConstantColorRGB_01_Value": {
					"type": "SColorRGB",
					"value": "#c2afa3"
				},
				"Clients": {
					"type": "TArray<SEntityTemplateReference>",
					"value": ["4aa97708bd3f57b5"],
					"postInit": true
				},
				"m_eidParent": {
					"type": "SEntityTemplateReference",
					"value": "4aa97708bd3f57b5",
					"postInit": true
				}
			}
		},
		"4aa97708bd3f57b5": {
			"parent": null,
			"name": "OUTFIT_Sean_M_Actor_v0",
			"factory": "00EC23CD5ED3321D",
			"blueprint": "00F08545F4143973",
			"properties": {
				"m_ResourceID": {
					"type": "ZRuntimeResourceID",
					"value": null
				},
				"m_fLODScale": { "type": "float32", "value": 1 },
				"m_mTransform": {
					"type": "SMatrix43",
					"value": {
						"rotation": { "x": 0, "y": 0, "z": 0 },
						"position": {
							"x": 1.943861961364746,
							"y": -1,
							"z": 0
						}
					}
				},
				"m_pBonesAndCollisionResource": {
					"type": "ZRuntimeResourceID",
					"value": {
						"resource": "003AAB3D2C739F59",
						"flag": "5F"
					}
				},
				"m_bUsePerVertexStiffness": {
					"type": "bool",
					"value": false
				},
				"m_bGlobalCollidersEnabled": {
					"type": "bool",
					"value": false
				},
				"m_bUsePerVertexDamping": {
					"type": "bool",
					"value": false
				},
				"m_bUseSkinningPosNormalConstrains": {
					"type": "bool",
					"value": false
				},
				"m_bUseSkinningNegNormalConstrains": {
					"type": "bool",
					"value": false
				},
				"m_fLODOffset": { "type": "float32", "value": 100 },
				"m_bLimitTranslation": { "type": "bool", "value": false },
				"m_fDamping": { "type": "float32", "value": 0.5 },
				"m_fWindConstant": {
					"type": "float32",
					"value": 0.10000000149011612
				},
				"m_eRootBone": {
					"type": "BoneId.Enum",
					"value": "PELVIS"
				},
				"m_bEnableAngularVelocityScale": {
					"type": "bool",
					"value": true
				},
				"m_eBendConstrainType": {
					"type": "EClothBendConstrainType",
					"value": "eClothBendConstrainType_Stick"
				},
				"m_fBendStiffness": { "type": "float32", "value": 0.5 },
				"m_fShearStiffness": { "type": "float32", "value": 0.5 },
				"m_fFrequency": { "type": "float32", "value": 60 },
				"m_nIterations": { "type": "uint32", "value": 2 },
				"m_eStretchConstrainType": {
					"type": "EClothStretchConstrainType",
					"value": "eClothBendConstrainType_None"
				},
				"m_aBodyParts": {
					"type": "TArray<SEntityTemplateReference>",
					"value": ["fe436f726f682172", "da75fa65fb026b3f"],
					"postInit": true
				},
				"m_LocalColliders": {
					"type": "TArray<SEntityTemplateReference>",
					"value": [],
					"postInit": true
				}
			}
		},
		"fe436f726f682172": {
			"parent": "4aa97708bd3f57b5",
			"name": "Security_Body",
			"factory": "[modules:/zbodypartentity.class].pc_entitytype",
			"blueprint": "[modules:/zbodypartentity.class].pc_entityblueprint",
			"properties": {
				"m_pMeshResource": {
					"type": "ZRuntimeResourceID",
					"value": {
						"resource": "001706CDDEFDA9CC",
						"flag": "5F"
					}
				}
			}
		},
		"3508c948f73a7c0d": {
			"parent": "4aa97708bd3f57b5",
			"name": "male_regular_sean_02_head_01",
			"factory": "00C368563638F1E2",
			"blueprint": "0075C00497C38094",
			"properties": {
				"1565884279": {
					"type": "IRenderMaterialEntity.EModifierOperation",
					"value": "eReplace"
				},
				"m_mTransform": {
					"type": "SMatrix43",
					"value": {
						"rotation": { "x": 0, "y": 0, "z": 0 },
						"position": { "x": 0, "y": 0, "z": 0 }
					}
				},
				"Clients": {
					"type": "TArray<SEntityTemplateReference>",
					"value": ["4aa97708bd3f57b5"]
				},
				"Texture2D_01_enab": { "type": "bool", "value": true },
				"Texture2D_01": {
					"type": "ZRuntimeResourceID",
					"value": {
						"resource": "0099271C0E736593",
						"flag": "5F"
					}
				},
				"Diffuse_Saturation_01_Value": {
					"type": "float32",
					"value": 0.5
				},
				"ConstantVector1D_01_Value_op": {
					"type": "IRenderMaterialEntity.EModifierOperation",
					"value": "eReplace"
				},
				"ConstantVector1D_01_Value": {
					"type": "float32",
					"value": 0.2199999988079071
				},
				"m_eidParent": {
					"type": "SEntityTemplateReference",
					"value": "4aa97708bd3f57b5"
				}
			}
		},
		"da75fa65fb026b3f": {
			"parent": "4aa97708bd3f57b5",
			"name": "Mesh_Head",
			"factory": "[modules:/zbodypartentity.class].pc_entitytype",
			"blueprint": "[modules:/zbodypartentity.class].pc_entityblueprint",
			"properties": {
				"m_pMeshResource": {
					"type": "ZRuntimeResourceID",
					"value": {
						"resource": "002157E65D436590",
						"flag": "5F"
					}
				}
			}
		}
	},
	"propertyOverrides": [],
	"overrideDeletes": [],
	"pinConnectionOverrides": [],
	"pinConnectionOverrideDeletes": [],
	"externalScenes": [],
	"subType": "template",
	"quickEntityVersion": 3.1,
	"extraFactoryDependencies": [],
	"extraBlueprintDependencies": [],
	"comments": []
}
