{
	"tempHash": "00776303B47551F8",
	"tbluHash": "00BB806F19823920",
	"rootEntity": "30eb3fa5d8d0a8ab",
	"entities": {
		"4bb5689bfa7b48a6": {
			"parent": "15e65a5f0c9cec2e",
			"name": "Var0",
			"template": "[modules:/zoutfitvariation.class].pc_entitytype",
			"blueprint": "[modules:/zoutfitvariation.class].pc_entityblueprint",
			"properties": {},
			"postInitProperties": {},
			"editorOnly": false,
			"platformSpecificPropertyValues": []
		},
		"30eb3fa5d8d0a8ab": {
			"parent": null,
			"name": "CHARSET_MarcoAbiatti",
			"template": "[modules:/zoutfitvariationcollection.class].pc_entitytype",
			"blueprint": "[modules:/zoutfitvariationcollection.class].pc_entityblueprint",
			"properties": {},
			"postInitProperties": {
				"m_aCharacters": {
					"type": "TArray<SEntityTemplateReference>",
					"value": ["44327df2b6cb33bc", "f7a023ef0ed5442d", "7fa21e2f584f58e4", "96068932d6880ef6", "15e65a5f0c9cec2e"]
				}
			},
			"editorOnly": false,
			"platformSpecificPropertyValues": []
		},
		"15e65a5f0c9cec2e": {
			"parent": "30eb3fa5d8d0a8ab",
			"name": "HeroC",
			"template": "[modules:/zcharsetcharactertype.class].pc_entitytype",
			"blueprint": "[modules:/zcharsetcharactertype.class].pc_entityblueprint",
			"properties": {
				"m_aVariations": {
					"type": "TArray<SEntityTemplateReference>",
					"value": ["4bb5689bfa7b48a6"]
				}
			},
			"postInitProperties": {},
			"editorOnly": false,
			"platformSpecificPropertyValues": []
		},
		"44327df2b6cb33bc": {
			"parent": "30eb3fa5d8d0a8ab",
			"name": "Actor",
			"template": "[modules:/zcharsetcharactertype.class].pc_entitytype",
			"blueprint": "[modules:/zcharsetcharactertype.class].pc_entityblueprint",
			"properties": {},
			"postInitProperties": {
				"m_aVariations": {
					"type": "TArray<SEntityTemplateReference>",
					"value": ["4e3f7eed897a96c4"]
				}
			},
			"editorOnly": false,
			"platformSpecificPropertyValues": []
		},
		"7fa21e2f584f58e4": {
			"parent": "30eb3fa5d8d0a8ab",
			"name": "HeroA",
			"template": "[modules:/zcharsetcharactertype.class].pc_entitytype",
			"blueprint": "[modules:/zcharsetcharactertype.class].pc_entityblueprint",
			"properties": {},
			"postInitProperties": {
				"m_aVariations": {
					"type": "TArray<SEntityTemplateReference>",
					"value": ["315f582f07fe8184"]
				}
			},
			"editorOnly": false,
			"platformSpecificPropertyValues": []
		},
		"f7a023ef0ed5442d": {
			"parent": "30eb3fa5d8d0a8ab",
			"name": "Nude",
			"template": "[modules:/zcharsetcharactertype.class].pc_entitytype",
			"blueprint": "[modules:/zcharsetcharactertype.class].pc_entityblueprint",
			"properties": {},
			"postInitProperties": {
				"m_aVariations": {
					"type": "TArray<SEntityTemplateReference>",
					"value": ["b2ad3a4032300aaf"]
				}
			},
			"editorOnly": false,
			"platformSpecificPropertyValues": []
		},
		"8c9f265436eae3d6": {
			"parent": "96068932d6880ef6",
			"name": "Var0",
			"template": "[modules:/zoutfitvariation.class].pc_entitytype",
			"blueprint": "[modules:/zoutfitvariation.class].pc_entityblueprint",
			"properties": {},
			"postInitProperties": {},
			"editorOnly": false,
			"platformSpecificPropertyValues": []
		},
		"96068932d6880ef6": {
			"parent": "30eb3fa5d8d0a8ab",
			"name": "HeroB",
			"template": "[modules:/zcharsetcharactertype.class].pc_entitytype",
			"blueprint": "[modules:/zcharsetcharactertype.class].pc_entityblueprint",
			"properties": {
				"m_aVariations": {
					"type": "TArray<SEntityTemplateReference>",
					"value": ["8c9f265436eae3d6"]
				}
			},
			"postInitProperties": {},
			"editorOnly": false,
			"platformSpecificPropertyValues": []
		},
		"4e3f7eed897a96c4": {
			"parent": "44327df2b6cb33bc",
			"name": "0",
			"template": "[modules:/zoutfitvariation.class].pc_entitytype",
			"blueprint": "[modules:/zoutfitvariation.class].pc_entityblueprint",
			"properties": {
				"m_Outfit": {
					"type": "ZRuntimeResourceID",
					"value": {
						"resource": "[assembly:/_pro/characters/templates/sapiensa/char_sapienza_unique.template?/outfit_marcoabiatti_actor_v0.entitytemplate].pc_entitytemplate",
						"flag": "9F"
					}
				}
			},
			"postInitProperties": {},
			"editorOnly": false,
			"platformSpecificPropertyValues": []
		},
		"b2ad3a4032300aaf": {
			"parent": "f7a023ef0ed5442d",
			"name": "Var0",
			"template": "[modules:/zoutfitvariation.class].pc_entitytype",
			"blueprint": "[modules:/zoutfitvariation.class].pc_entityblueprint",
			"properties": {
				"m_Outfit": {
					"type": "ZRuntimeResourceID",
					"value": {
						"resource": "004C5C599713CCBF\n",
						"flag": "9F"
					}
				}
			},
			"postInitProperties": {},
			"editorOnly": false,
			"platformSpecificPropertyValues": []
		},
		"315f582f07fe8184": {
			"parent": "7fa21e2f584f58e4",
			"name": "Var0",
			"template": "[modules:/zoutfitvariation.class].pc_entitytype",
			"blueprint": "[modules:/zoutfitvariation.class].pc_entityblueprint",
			"properties": {
				"m_Outfit": {
					"type": "ZRuntimeResourceID",
					"value": {
						"resource": "0054E8B4457E59F6\n",
						"flag": "9F"
					}
				}
			},
			"postInitProperties": {},
			"editorOnly": false,
			"platformSpecificPropertyValues": []
		}
	},
	"overrideDeletes": [],
	"pinConnectionOverrides": [],
	"pinConnectionOverrideDeletes": [],
	"propertyOverrides": [],
	"externalScenes": [],
	"subType": 0,
	"quickEntityVersion": 2.1
}