{"tempHash":"000F451301B9E4E2","tbluHash":"008DDD05BA0A11FA","rootEntity":"3dbed19c60e8b7e3","entities":{"f219b37b6a341b08":{"parent":"3dbed19c60e8b7e3","name":"Head_47","factory":"00537D16B5CE7286","blueprint":"00F2E4A932ECAA63"},"0dc758a1490817b0":{"parent":"3dbed19c60e8b7e3","name":"Shirt_Btnup_RldSlv_Open","factory":"007C24D8BEBBA923","blueprint":"00CE401D89902DFC","properties":{"Diffuse_Color_01_Value":{"type":"SColorRGB","value":"#7a9986"}}},"bcf8d0741e75ee42":{"parent":"3dbed19c60e8b7e3","name":"TShirt_CrewNeck_Cut_Jacket","factory":"007A2182865B9610","blueprint":"009EDBC596AFF5DA","properties":{"Diffuse_Color_01_Value":{"type":"SColorRGB","value":"#de854e"}}},"7f6b475c96117a4c":{"parent":"3dbed19c60e8b7e3","name":"Belt_StrapBuckle","factory":"0017355DDB3D75A3","blueprint":"005F1B0540C7F863","properties":{"Diffuse_Color_01_Value":{"type":"SColorRGB","value":"#52463c"}}},"3dbed19c60e8b7e3":{"parent":null,"name":"OUTFIT_Mongoose_Civilian_Rich_M_Actor_v2","factory":"00C0753FBF784C66","blueprint":"007294473357329E","properties":{"m_LocalColliders":{"type":"TArray<SEntityTemplateReference>","value":[]},"m_mTransform":{"type":"SMatrix43","value":{"rotation":{"x":0,"y":0,"z":0},"position":{"x":4.044517993927002,"y":-0.000001446927967663214,"z":0}}},"m_aBodyParts":{"type":"TArray<SEntityTemplateReference>","value":["e7ea4cf42fb00e28","f219b37b6a341b08","0dc758a1490817b0","52e3bf2ae4ee63a3","a01e3ceb777f7e6c","bcf8d0741e75ee42","65d9076442106cb8","7f6b475c96117a4c"],"postInit":true}}},"65d9076442106cb8":{"parent":"3dbed19c60e8b7e3","name":"Torso_Full","factory":"00A5D4779E6AA927","blueprint":"00B53E161DA42DC5"},"6007a0c74b926c41":{"parent":"5cfe013ed292147d","name":"Bracelet_Leather_Strap","factory":"001F119BFAE57CF7","blueprint":"00DFC51C8ADFB832","properties":{"m_mTransform":{"type":"SMatrix43","value":{"rotation":{"x":-1.31574821472168,"y":-0.18185709416866302,"z":-90.14592742919922},"position":{"x":0.2325170934200287,"y":-0.0007590103195980191,"z":0.005127999931573868},"scale":{"x":1.0000000000000002,"y":1,"z":1}}},"m_PrimitiveScale":{"type":"SVector3","value":{"x":1,"y":1,"z":1}},"m_eidParent":{"type":"SEntityTemplateReference","value":"5cfe013ed292147d","postInit":true}}},"5cfe013ed292147d":{"parent":"3dbed19c60e8b7e3","name":"Attacher_Wrist_L","factory":"[assembly:/templates/aspectdummy.aspect]([modules:/zcompositeentity.class].entitytype,[modules:/zboneattachaspect.class].entitytype).pc_entitytype","blueprint":"[assembly:/templates/aspectdummy.aspect]([modules:/zcompositeentity.class].entitytype,[modules:/zboneattachaspect.class].entitytype).pc_entityblueprint","properties":{"m_BoneName":{"type":"ZString","value":"L_Forearm"},"m_linkedEntity":{"type":"SEntityTemplateReference","value":"3dbed19c60e8b7e3"},"m_mTransform":{"type":"SMatrix43","value":{"rotation":{"x":0,"y":0,"z":-0.0000000000000031805545068312735},"position":{"x":0,"y":0.00000000000000039931589529114755,"z":0}}},"m_eidParent":{"type":"SEntityTemplateReference","value":"3dbed19c60e8b7e3"}}},"e7ea4cf42fb00e28":{"parent":"3dbed19c60e8b7e3","name":"Arms_Biceps_Hand","factory":"0081BA55B3D8292E","blueprint":"00CFA61BB1571AF8"},"52e3bf2ae4ee63a3":{"parent":"3dbed19c60e8b7e3","name":"Shoes_Sneakers_Skate","factory":"0051CDBE526A5788","blueprint":"005E95DA5C8F37F9"},"a01e3ceb777f7e6c":{"parent":"3dbed19c60e8b7e3","name":"Pants_Jeans_Slim","factory":"00D8F98FFC2766FE","blueprint":"0027BE58478DD2EC","properties":{"Diffuse_Color_01_Value":{"type":"SColorRGB","value":"#545454"}}}},"propertyOverrides":[],"overrideDeletes":[],"pinConnectionOverrides":[],"pinConnectionOverrideDeletes":[],"externalScenes":[],"subType":"template","quickEntityVersion":3.1,"extraFactoryDependencies":[],"extraBlueprintDependencies":[],"comments":[]}