{
	"tempHash": "005881F6F479EEBF",
	"tbluHash": "0089B410C893DF68",
	"rootEntity": "65e0396981b14ff6",
	"entities": {
		"926f453ed27ad3b7": {
			"parent": "65e0396981b14ff6",
			"name": "Head_47",
			"template": "00537D16B5CE7286",
			"blueprint": "00F2E4A932ECAA63",
			"properties": {},
			"postInitProperties": {},
			"editorOnly": false,
			"platformSpecificPropertyValues": []
		},
		"726f46be81252bd5": {
			"parent": "65e0396981b14ff6",
			"name": "Hat_Bucket",
			"template": "[modules:/zbodypartentity.class].pc_entitytype",
			"blueprint": "[modules:/zbodypartentity.class].pc_entityblueprint",
			"properties": {
				"m_pMeshResource": {
					"type": "ZRuntimeResourceID",
					"value": {
						"resource": "[assembly:/_pro/characters/assets/individuals/bulldog/privateinvestigator/geometry/male_reg_privateinvestigator.wl2?/hat_bucket.weightedprim](bodypart).pc_weightedprim",
						"flag": "5F"
					}
				}
			},
			"postInitProperties": {},
			"editorOnly": false,
			"platformSpecificPropertyValues": []
		},
		"87ca78109283e288": {
			"parent": "65e0396981b14ff6",
			"name": "Belt_StrapBuckle_StuddedCircle",
			"template": "0000E7BC5A6C96BB",
			"blueprint": "00E44B5B62C72207",
			"properties": {
				"m_pMeshResource": {
					"type": "ZRuntimeResourceID",
					"value": {
						"resource": "0008D51FF04FF294",
						"flag": "5F"
					}
				}
			},
			"postInitProperties": {},
			"editorOnly": false,
			"platformSpecificPropertyValues": []
		},
		"5371e11f2ee44b9e": {
			"parent": "953af237732cbd82",
			"name": "C_Knee_L",
			"template": "[assembly:/templates/aspectdummy.aspect]([modules:/zclothsphere.class].entitytype,[modules:/zboneattachaspect.class].entitytype).pc_entitytype",
			"blueprint": "[assembly:/templates/aspectdummy.aspect]([modules:/zclothsphere.class].entitytype,[modules:/zboneattachaspect.class].entitytype).pc_entityblueprint",
			"properties": {
				"m_fRadius": {
					"type": "float32",
					"value": 0.070000000298023224
				},
				"m_BoneName": {
					"type": "ZString",
					"value": "L_Calf"
				},
				"m_mTransform": {
					"type": "SMatrix43",
					"value": {
						"rotation": {
							"x": 0,
							"y": 0,
							"z": 0
						},
						"position": {
							"x": 0.0012860000133514404,
							"y": -0.006829000078141689,
							"z": -0.007672999985516071
						}
					}
				}
			},
			"postInitProperties": {
				"m_eidParent": {
					"type": "SEntityTemplateReference",
					"value": "953af237732cbd82"
				}
			},
			"editorOnly": false,
			"platformSpecificPropertyValues": []
		},
		"7a4f495d5184f146": {
			"parent": "65e0396981b14ff6",
			"name": "Shoes_Sneakers_Standard",
			"template": "001CEDC5CA47F844",
			"blueprint": "009CE096277BA564",
			"properties": {
				"Texture2D_01": {
					"type": "ZRuntimeResourceID",
					"value": {
						"resource": "004A7941F89B2729",
						"flag": "5F"
					}
				}
			},
			"postInitProperties": {},
			"editorOnly": false,
			"platformSpecificPropertyValues": []
		},
		"222260b20f8040ac": {
			"parent": "95fd9e2d66d53952",
			"name": "male_reg_silviocaruso_necklace_01",
			"template": "[assembly:/_pro/characters/assets/individuals/italy/silviocaruso/materials/male_reg_silviocaruso_necklace_01.mi].pc_entitytype",
			"blueprint": "[assembly:/_pro/characters/assets/individuals/italy/silviocaruso/materials/male_reg_silviocaruso_necklace_01.mi].pc_entityblueprint",
			"properties": {
				"m_mTransform": {
					"type": "SMatrix43",
					"value": {
						"rotation": {
							"x": 0,
							"y": 0,
							"z": 0
						},
						"position": {
							"x": 0,
							"y": 0,
							"z": 0
						}
					}
				},
				"Texture2D_03_enab": {
					"type": "bool",
					"value": true
				},
				"Texture2D_03": {
					"type": "ZRuntimeResourceID",
					"value": {
						"resource": "[assembly:/_pro/characters/assets/individuals/italy/silviocaruso/textures/male_reg_silviocaruso_necklace_01.texture?/specular_b.tex](ascolormap).pc_tex",
						"flag": "5F"
					}
				},
				"Texture2D_01_enab": {
					"type": "bool",
					"value": true
				},
				"Texture2D_01": {
					"type": "ZRuntimeResourceID",
					"value": {
						"resource": "[assembly:/_pro/characters/assets/individuals/italy/silviocaruso/textures/male_reg_silviocaruso_necklace_01.texture?/diffuse_b.tex](ascolormap).pc_tex",
						"flag": "5F"
					}
				},
				"ConstantVector1D_01_Value_op": {
					"type": "IRenderMaterialEntity.EModifierOperation",
					"value": "eReplace"
				},
				"ConstantVector1D_01_Value": {
					"type": "float32",
					"value": 0.20999999344348907
				}
			},
			"postInitProperties": {
				"Clients": {
					"type": "TArray<SEntityTemplateReference>",
					"value": ["95fd9e2d66d53952"]
				},
				"m_eidParent": {
					"type": "SEntityTemplateReference",
					"value": "95fd9e2d66d53952"
				}
			},
			"editorOnly": false,
			"platformSpecificPropertyValues": []
		},
		"e4c89fe00a689348": {
			"parent": "953af237732cbd82",
			"name": "C_Spine1_R",
			"template": "[assembly:/templates/aspectdummy.aspect]([modules:/zclothsphere.class].entitytype,[modules:/zboneattachaspect.class].entitytype).pc_entitytype",
			"blueprint": "[assembly:/templates/aspectdummy.aspect]([modules:/zclothsphere.class].entitytype,[modules:/zboneattachaspect.class].entitytype).pc_entityblueprint",
			"properties": {
				"m_BoneName": {
					"type": "ZString",
					"value": "Spine1"
				},
				"m_fRadius": {
					"type": "float32",
					"value": 0.125
				},
				"m_mTransform": {
					"type": "SMatrix43",
					"value": {
						"rotation": {
							"x": -0.0312834939246248,
							"y": 0,
							"z": 0
						},
						"position": {
							"x": -0.030838999897241592,
							"y": 0.02711400017142296,
							"z": -0.04226800054311752
						}
					}
				},
				"m_bEnabled": {
					"type": "bool",
					"value": true
				}
			},
			"postInitProperties": {
				"m_eidParent": {
					"type": "SEntityTemplateReference",
					"value": "953af237732cbd82"
				}
			},
			"editorOnly": false,
			"platformSpecificPropertyValues": []
		},
		"a215dc85f68e188": {
			"parent": "65e0396981b14ff6",
			"name": "Arms_Biceps_Hand",
			"template": "0081BA55B3D8292E",
			"blueprint": "00CFA61BB1571AF8",
			"properties": {},
			"postInitProperties": {},
			"editorOnly": false,
			"platformSpecificPropertyValues": []
		},
		"5eea0e4a7d7e8d85": {
			"parent": "953af237732cbd82",
			"name": "C_Spine1_L",
			"template": "[assembly:/templates/aspectdummy.aspect]([modules:/zclothsphere.class].entitytype,[modules:/zboneattachaspect.class].entitytype).pc_entitytype",
			"blueprint": "[assembly:/templates/aspectdummy.aspect]([modules:/zclothsphere.class].entitytype,[modules:/zboneattachaspect.class].entitytype).pc_entityblueprint",
			"properties": {
				"m_BoneName": {
					"type": "ZString",
					"value": "Spine1"
				},
				"m_fRadius": {
					"type": "float32",
					"value": 0.125
				},
				"m_mTransform": {
					"type": "SMatrix43",
					"value": {
						"rotation": {
							"x": -0.0312834939246248,
							"y": 0,
							"z": 0
						},
						"position": {
							"x": -0.0316540002822876,
							"y": 0.035999998450279236,
							"z": 0.0381769984960556
						}
					}
				},
				"m_bEnabled": {
					"type": "bool",
					"value": true
				}
			},
			"postInitProperties": {
				"m_eidParent": {
					"type": "SEntityTemplateReference",
					"value": "953af237732cbd82"
				}
			},
			"editorOnly": false,
			"platformSpecificPropertyValues": []
		},
		"f3a9fead7a5fcc41": {
			"parent": "953af237732cbd82",
			"name": "C_Spine2_L",
			"template": "[assembly:/templates/aspectdummy.aspect]([modules:/zclothsphere.class].entitytype,[modules:/zboneattachaspect.class].entitytype).pc_entitytype",
			"blueprint": "[assembly:/templates/aspectdummy.aspect]([modules:/zclothsphere.class].entitytype,[modules:/zboneattachaspect.class].entitytype).pc_entityblueprint",
			"properties": {
				"m_BoneName": {
					"type": "ZString",
					"value": "Spine2"
				},
				"m_fRadius": {
					"type": "float32",
					"value": 0.15000000596046448
				},
				"m_mTransform": {
					"type": "SMatrix43",
					"value": {
						"rotation": {
							"x": 0.7218317539587317,
							"y": 0.04915978565467651,
							"z": 7.7893839530248785
						},
						"position": {
							"x": -0.0348690003156662,
							"y": 0.02468400076031685,
							"z": 0.040442001074552536
						}
					}
				},
				"m_bEnabled": {
					"type": "bool",
					"value": true
				}
			},
			"postInitProperties": {
				"m_eidParent": {
					"type": "SEntityTemplateReference",
					"value": "953af237732cbd82"
				}
			},
			"editorOnly": false,
			"platformSpecificPropertyValues": []
		},
		"52f9dc87471a25e6": {
			"parent": "953af237732cbd82",
			"name": "C_Spine_R",
			"template": "[assembly:/templates/aspectdummy.aspect]([modules:/zclothsphere.class].entitytype,[modules:/zboneattachaspect.class].entitytype).pc_entitytype",
			"blueprint": "[assembly:/templates/aspectdummy.aspect]([modules:/zclothsphere.class].entitytype,[modules:/zboneattachaspect.class].entitytype).pc_entityblueprint",
			"properties": {
				"m_BoneName": {
					"type": "ZString",
					"value": "Spine"
				},
				"m_fRadius": {
					"type": "float32",
					"value": 0.12999999523162842
				},
				"m_mTransform": {
					"type": "SMatrix43",
					"value": {
						"rotation": {
							"x": -0.05930116869051336,
							"y": 0.048472234150680464,
							"z": -0.06250973638926272
						},
						"position": {
							"x": -1.9999999949504854e-06,
							"y": 0.030573999509215355,
							"z": -0.050732001662254333
						}
					}
				},
				"m_bEnabled": {
					"type": "bool",
					"value": true
				},
				"m_bCollisionGroup0": {
					"type": "bool",
					"value": true
				}
			},
			"postInitProperties": {
				"m_eidParent": {
					"type": "SEntityTemplateReference",
					"value": "953af237732cbd82"
				}
			},
			"editorOnly": false,
			"platformSpecificPropertyValues": []
		},
		"bf646f13e07b5c0f": {
			"parent": "953af237732cbd82",
			"name": "C_Pelvis_L",
			"template": "[assembly:/templates/aspectdummy.aspect]([modules:/zclothsphere.class].entitytype,[modules:/zboneattachaspect.class].entitytype).pc_entitytype",
			"blueprint": "[assembly:/templates/aspectdummy.aspect]([modules:/zclothsphere.class].entitytype,[modules:/zboneattachaspect.class].entitytype).pc_entityblueprint",
			"properties": {
				"m_fRadius": {
					"type": "float32",
					"value": 0.14000000059604645
				},
				"m_BoneName": {
					"type": "ZString",
					"value": "Pelvis"
				},
				"m_mTransform": {
					"type": "SMatrix43",
					"value": {
						"rotation": {
							"x": -0.055977958130533356,
							"y": 0,
							"z": -0.055977958130533356
						},
						"position": {
							"x": 0.03650100156664848,
							"y": 0.016163000836968422,
							"z": 0.05415499955415726
						}
					}
				},
				"m_bEnabled": {
					"type": "bool",
					"value": true
				}
			},
			"postInitProperties": {
				"m_eidParent": {
					"type": "SEntityTemplateReference",
					"value": "953af237732cbd82"
				}
			},
			"editorOnly": false,
			"platformSpecificPropertyValues": []
		},
		"48a1116308a21bcc": {
			"parent": "953af237732cbd82",
			"name": "CChain_Legs",
			"template": "[modules:/zclothspherechain.class].pc_entitytype",
			"blueprint": "[modules:/zclothspherechain.class].pc_entityblueprint",
			"properties": {
				"m_mTransform": {
					"type": "SMatrix43",
					"value": {
						"rotation": {
							"x": 0,
							"y": 0,
							"z": 0
						},
						"position": {
							"x": -1.290655973207322e-07,
							"y": 2.171457902377938e-09,
							"z": 0
						}
					}
				},
				"m_bCollisionGroup0": {
					"type": "bool",
					"value": true
				},
				"m_bEnabled": {
					"type": "bool",
					"value": true
				}
			},
			"postInitProperties": {
				"m_Spheres": {
					"type": "TArray<SEntityTemplateReference>",
					"value": ["e3473b2342b29aee", "8bdcca8ce11e0d1b", "bb8eaa6fe4d1f2d6", "1114738fa3dc3219", "bf646f13e07b5c0f", "616f24e83f2dbaec", "374a936d9982adb6", "5371e11f2ee44b9e"]
				},
				"m_eidParent": {
					"type": "SEntityTemplateReference",
					"value": "953af237732cbd82"
				}
			},
			"editorOnly": false,
			"platformSpecificPropertyValues": []
		},
		"9b97daedd7b1a191": {
			"parent": "65e0396981b14ff6",
			"name": "Attacher_Head",
			"template": "[assembly:/templates/aspectdummy.aspect]([modules:/zcompositeentity.class].entitytype,[modules:/zboneattachaspect.class].entitytype).pc_entitytype",
			"blueprint": "[assembly:/templates/aspectdummy.aspect]([modules:/zcompositeentity.class].entitytype,[modules:/zboneattachaspect.class].entitytype).pc_entityblueprint",
			"properties": {
				"m_BoneName": {
					"type": "ZString",
					"value": "Head"
				}
			},
			"postInitProperties": {
				"m_linkedEntity": {
					"type": "SEntityTemplateReference",
					"value": "65e0396981b14ff6"
				},
				"m_eidParent": {
					"type": "SEntityTemplateReference",
					"value": "65e0396981b14ff6"
				}
			},
			"editorOnly": false,
			"platformSpecificPropertyValues": []
		},
		"1114738fa3dc3219": {
			"parent": "953af237732cbd82",
			"name": "C_Pelvis_R",
			"template": "[assembly:/templates/aspectdummy.aspect]([modules:/zclothsphere.class].entitytype,[modules:/zboneattachaspect.class].entitytype).pc_entitytype",
			"blueprint": "[assembly:/templates/aspectdummy.aspect]([modules:/zclothsphere.class].entitytype,[modules:/zboneattachaspect.class].entitytype).pc_entityblueprint",
			"properties": {
				"m_fRadius": {
					"type": "float32",
					"value": 0.12999999523162842
				},
				"m_BoneName": {
					"type": "ZString",
					"value": "Pelvis"
				},
				"m_mTransform": {
					"type": "SMatrix43",
					"value": {
						"rotation": {
							"x": -0.055977958130533356,
							"y": 0,
							"z": -0.055977958130533356
						},
						"position": {
							"x": 0.03649599850177765,
							"y": 0.016163000836968422,
							"z": -0.05660700052976608
						}
					}
				},
				"m_bEnabled": {
					"type": "bool",
					"value": true
				}
			},
			"postInitProperties": {
				"m_eidParent": {
					"type": "SEntityTemplateReference",
					"value": "953af237732cbd82"
				}
			},
			"editorOnly": false,
			"platformSpecificPropertyValues": []
		},
		"e9883e9dfa949d7": {
			"parent": "726f46be81252bd5",
			"name": "male_reg_locals_04_hat_02",
			"template": "[assembly:/_pro/characters/assets/civilians/italy/local_mens/materials/male_reg_locals_04_hat_02.mi].pc_entitytype",
			"blueprint": "[assembly:/_pro/characters/assets/civilians/italy/local_mens/materials/male_reg_locals_04_hat_02.mi].pc_entityblueprint",
			"properties": {
				"1294887455": {
					"type": "IRenderMaterialEntity.EModifierOperation",
					"value": "eReplace"
				},
				"1787395739": {
					"type": "IRenderMaterialEntity.EModifierOperation",
					"value": "eReplace"
				},
				"2786709788": {
					"type": "IRenderMaterialEntity.EModifierOperation",
					"value": "eReplace"
				},
				"2869403995": {
					"type": "IRenderMaterialEntity.EModifierOperation",
					"value": "eReplace"
				},
				"3516673141": {
					"type": "IRenderMaterialEntity.EModifierOperation",
					"value": "eReplace"
				},
				"m_mTransform": {
					"type": "SMatrix43",
					"value": {
						"rotation": {
							"x": 0,
							"y": 0,
							"z": 0
						},
						"position": {
							"x": 0,
							"y": 0,
							"z": 0
						}
					}
				},
				"Clients": {
					"type": "TArray<SEntityTemplateReference>",
					"value": ["726f46be81252bd5"]
				},
				"Texture2D_01_enab": {
					"type": "bool",
					"value": false
				},
				"Texture2DNormal_01_enab": {
					"type": "bool",
					"value": true
				},
				"Texture2DNormal_01": {
					"type": "ZRuntimeResourceID",
					"value": {
						"resource": "00F1F070E180AD4F",
						"flag": "5F"
					}
				},
				"Texture2D_01": {
					"type": "ZRuntimeResourceID",
					"value": {
						"resource": "00E3DCCCB9318C54",
						"flag": "5F"
					}
				},
				"Diffuse_Color_01_Value": {
					"type": "SColorRGB",
					"value": "#575757"
				},
				"ConstantVector1D_01_Value_op": {
					"type": "IRenderMaterialEntity.EModifierOperation",
					"value": "eReplace"
				},
				"ConstantVector1D_01_Value": {
					"type": "float32",
					"value": 1.2000000476837158
				},
				"ConstantVector1D_03_Value": {
					"type": "float32",
					"value": 0.5
				},
				"Texture2D_03_enab": {
					"type": "bool",
					"value": true
				},
				"ConstantVector1D_13_Value": {
					"type": "float32",
					"value": 0
				},
				"ConstantVector1D_16_Value": {
					"type": "float32",
					"value": 0
				}
			},
			"postInitProperties": {
				"m_eidParent": {
					"type": "SEntityTemplateReference",
					"value": "65e0396981b14ff6"
				}
			},
			"editorOnly": false,
			"platformSpecificPropertyValues": []
		},
		"3d7b3c09731d7ae2": {
			"parent": "9b97daedd7b1a191",
			"name": "glasses_vintage",
			"template": "00A3FEE4A2173105",
			"blueprint": "0030DE280B901672",
			"properties": {
				"m_mTransform": {
					"type": "SMatrix43",
					"value": {
						"rotation": {
							"x": -3.612888823468572,
							"y": 88.81733248935218,
							"z": -176.98531505097282
						},
						"position": {
							"x": 0.07073800265789032,
							"y": 0.002836999949067831,
							"z": 0.0002530000056140125
						}
					}
				},
				"m_PrimitiveScale": {
					"type": "SVector3",
					"value": {
						"x": 1.0299999713897705,
						"y": 1.0299999713897705,
						"z": 1.0099999904632568
					}
				},
				"ConstantVector1D_01_Value": {
					"type": "float32",
					"value": 0.5
				},
				"Diffuse_Tint_Value": {
					"type": "SColorRGB",
					"value": "#171414"
				},
				"m_eidParent": {
					"type": "SEntityTemplateReference",
					"value": "9b97daedd7b1a191"
				}
			},
			"postInitProperties": {},
			"editorOnly": false,
			"platformSpecificPropertyValues": []
		},
		"34e34008338e1530": {
			"parent": "953af237732cbd82",
			"name": "C_Spine_L",
			"template": "[assembly:/templates/aspectdummy.aspect]([modules:/zclothsphere.class].entitytype,[modules:/zboneattachaspect.class].entitytype).pc_entitytype",
			"blueprint": "[assembly:/templates/aspectdummy.aspect]([modules:/zclothsphere.class].entitytype,[modules:/zboneattachaspect.class].entitytype).pc_entityblueprint",
			"properties": {
				"m_BoneName": {
					"type": "ZString",
					"value": "Spine"
				},
				"m_fRadius": {
					"type": "float32",
					"value": 0.12999999523162842
				},
				"m_mTransform": {
					"type": "SMatrix43",
					"value": {
						"rotation": {
							"x": -0.055977958130533356,
							"y": 0,
							"z": -0.055977958130533356
						},
						"position": {
							"x": 9.999999974752427e-07,
							"y": 0.032037001103162766,
							"z": 0.04795899987220764
						}
					}
				},
				"m_bEnabled": {
					"type": "bool",
					"value": true
				},
				"m_bCollisionGroup0": {
					"type": "bool",
					"value": true
				}
			},
			"postInitProperties": {
				"m_eidParent": {
					"type": "SEntityTemplateReference",
					"value": "953af237732cbd82"
				}
			},
			"editorOnly": false,
			"platformSpecificPropertyValues": []
		},
		"bb8eaa6fe4d1f2d6": {
			"parent": "953af237732cbd82",
			"name": "C_TighTop_R",
			"template": "[assembly:/templates/aspectdummy.aspect]([modules:/zclothsphere.class].entitytype,[modules:/zboneattachaspect.class].entitytype).pc_entitytype",
			"blueprint": "[assembly:/templates/aspectdummy.aspect]([modules:/zclothsphere.class].entitytype,[modules:/zboneattachaspect.class].entitytype).pc_entityblueprint",
			"properties": {
				"m_fRadius": {
					"type": "float32",
					"value": 0.12999999523162842
				},
				"m_BoneName": {
					"type": "ZString",
					"value": "RThighTwist"
				},
				"m_mTransform": {
					"type": "SMatrix43",
					"value": {
						"rotation": {
							"x": 0,
							"y": 0,
							"z": 0
						},
						"position": {
							"x": 0.001196000026538968,
							"y": 0.022128000855445862,
							"z": -0.032802000641822815
						}
					}
				}
			},
			"postInitProperties": {
				"m_eidParent": {
					"type": "SEntityTemplateReference",
					"value": "953af237732cbd82"
				}
			},
			"editorOnly": false,
			"platformSpecificPropertyValues": []
		},
		"616f24e83f2dbaec": {
			"parent": "953af237732cbd82",
			"name": "C_TighTop_L",
			"template": "[assembly:/templates/aspectdummy.aspect]([modules:/zclothsphere.class].entitytype,[modules:/zboneattachaspect.class].entitytype).pc_entitytype",
			"blueprint": "[assembly:/templates/aspectdummy.aspect]([modules:/zclothsphere.class].entitytype,[modules:/zboneattachaspect.class].entitytype).pc_entityblueprint",
			"properties": {
				"m_fRadius": {
					"type": "float32",
					"value": 0.14000000059604645
				},
				"m_BoneName": {
					"type": "ZString",
					"value": "LThighTwist"
				},
				"m_mTransform": {
					"type": "SMatrix43",
					"value": {
						"rotation": {
							"x": 0,
							"y": 0.019767044762768395,
							"z": 0
						},
						"position": {
							"x": 0.001041000010445714,
							"y": 0.013353000394999981,
							"z": 0.03816999867558479
						}
					}
				}
			},
			"postInitProperties": {
				"m_eidParent": {
					"type": "SEntityTemplateReference",
					"value": "953af237732cbd82"
				}
			},
			"editorOnly": false,
			"platformSpecificPropertyValues": []
		},
		"65e0396981b14ff6": {
			"parent": null,
			"name": "OUTFIT_Fox_Civilian_Raver_M_Actor_v8",
			"template": "00028BAEA86DD2FD",
			"blueprint": "002045A6D2A25237",
			"properties": {
				"m_pBonesAndCollisionResource": {
					"type": "ZRuntimeResourceID",
					"value": {
						"resource": "00E6D746D26D3871",
						"flag": "5F"
					}
				},
				"m_eRoomBehaviour": {
					"type": "ZSpatialEntity.ERoomBehaviour",
					"value": "ROOM_DYNAMIC"
				},
				"m_mTransform": {
					"type": "SMatrix43",
					"value": {
						"rotation": {
							"x": 0,
							"y": 0,
							"z": 0
						},
						"position": {
							"x": 15.586210250854492,
							"y": 0.7694140076637268,
							"z": -1.158486008644104
						}
					}
				},
				"m_BodyPartLODCutOffMeshResource": {
					"type": "ZRuntimeResourceID",
					"value": {
						"resource": "0010C57E70B56C1B",
						"flag": "5F"
					}
				},
				"m_nBodypartLODCutOff": {
					"type": "uint32",
					"value": 8
				},
				"m_bSimulationEnabled": {
					"type": "bool",
					"value": true
				}
			},
			"postInitProperties": {
				"m_aBodyParts": {
					"type": "TArray<SEntityTemplateReference>",
					"value": ["926f453ed27ad3b7", "7a4f495d5184f146", "554ce92786b4b570", "5960b240f2cd0b61", "87ca78109283e288", "95fd9e2d66d53952", "a215dc85f68e188", "bf93355e48ea16c1", "726f46be81252bd5"]
				}
			},
			"editorOnly": false,
			"platformSpecificPropertyValues": []
		},
		"79f068db5f897ceb": {
			"parent": "65e0396981b14ff6",
			"name": "Head_Attacher",
			"template": "[assembly:/templates/aspectdummy.aspect]([modules:/zcompositeentity.class].entitytype,[modules:/zboneattachaspect.class].entitytype).pc_entitytype",
			"blueprint": "[assembly:/templates/aspectdummy.aspect]([modules:/zcompositeentity.class].entitytype,[modules:/zboneattachaspect.class].entitytype).pc_entityblueprint",
			"properties": {
				"m_BoneName": {
					"type": "ZString",
					"value": "Head"
				},
				"m_linkedEntity": {
					"type": "SEntityTemplateReference",
					"value": "65e0396981b14ff6"
				},
				"m_mTransform": {
					"type": "SMatrix43",
					"value": {
						"rotation": {
							"x": 0,
							"y": 0,
							"z": 0
						},
						"position": {
							"x": 0,
							"y": 0,
							"z": 0
						}
					}
				},
				"m_eidParent": {
					"type": "SEntityTemplateReference",
					"value": "65e0396981b14ff6"
				}
			},
			"postInitProperties": {},
			"editorOnly": false,
			"platformSpecificPropertyValues": []
		},
		"ba4085bde0d955d3": {
			"parent": "953af237732cbd82",
			"name": "CChain_Spine_L",
			"template": "[modules:/zclothspherechain.class].pc_entitytype",
			"blueprint": "[modules:/zclothspherechain.class].pc_entityblueprint",
			"properties": {
				"m_Spheres": {
					"type": "TArray<SEntityTemplateReference>",
					"value": ["34e34008338e1530", "5eea0e4a7d7e8d85", "f3a9fead7a5fcc41"]
				},
				"m_mTransform": {
					"type": "SMatrix43",
					"value": {
						"rotation": {
							"x": 0,
							"y": 0,
							"z": 0
						},
						"position": {
							"x": -1.290655973207322e-07,
							"y": 2.171457902377938e-09,
							"z": 0
						}
					}
				}
			},
			"postInitProperties": {
				"m_eidParent": {
					"type": "SEntityTemplateReference",
					"value": "953af237732cbd82"
				}
			},
			"editorOnly": false,
			"platformSpecificPropertyValues": []
		},
		"a8cf0fb9b8f8d752": {
			"parent": "95fd9e2d66d53952",
			"name": "Mesh",
			"template": "[assembly:/templates/aspectdummy.aspect]([modules:/zbodypartentity.class].entitytype,[modules:/zclothcollidergroupaspect.class].entitytype).pc_entitytype",
			"blueprint": "[assembly:/templates/aspectdummy.aspect]([modules:/zbodypartentity.class].entitytype,[modules:/zclothcollidergroupaspect.class].entitytype).pc_entityblueprint",
			"properties": {
				"m_pMeshResource": {
					"type": "ZRuntimeResourceID",
					"value": {
						"resource": "00E66FA8E9BF68A6",
						"flag": "5F"
					}
				}
			},
			"postInitProperties": {
				"m_ClothColliders": {
					"type": "TArray<SEntityTemplateReference>",
					"value": ["953af237732cbd82"]
				}
			},
			"editorOnly": false,
			"platformSpecificPropertyValues": []
		},
		"95fd9e2d66d53952": {
			"parent": "65e0396981b14ff6",
			"name": "Waist_Chains_Left",
			"template": "[modules:/zcompositeentity.class].pc_entitytype",
			"blueprint": "[modules:/zcompositeentity.class].pc_entityblueprint",
			"properties": {
				"m_pMeshResource": {
					"type": "ZRuntimeResourceID",
					"value": {
						"resource": "00E66FA8E9BF68A6",
						"flag": "5F"
					}
				},
				"m_eidParent": {
					"type": "SEntityTemplateReference",
					"value": "65e0396981b14ff6"
				}
			},
			"postInitProperties": {},
			"editorOnly": false,
			"platformSpecificPropertyValues": [],
			"propertyAliases": [{
				"exposeProperty": "m_pMeshResource",
				"onEntity": "a8cf0fb9b8f8d752",
				"asProperty": "m_pMeshResource"
			}],
			"exposedInterfaces": [
				["ZBodyPartEntity", "a8cf0fb9b8f8d752"],
				["ZClothColliderGroupAspect", "a8cf0fb9b8f8d752"]
			]
		},
		"374a936d9982adb6": {
			"parent": "953af237732cbd82",
			"name": "C_TighMid_L",
			"template": "[assembly:/templates/aspectdummy.aspect]([modules:/zclothsphere.class].entitytype,[modules:/zboneattachaspect.class].entitytype).pc_entitytype",
			"blueprint": "[assembly:/templates/aspectdummy.aspect]([modules:/zclothsphere.class].entitytype,[modules:/zboneattachaspect.class].entitytype).pc_entityblueprint",
			"properties": {
				"m_fRadius": {
					"type": "float32",
					"value": 0.10499999672174454
				},
				"m_BoneName": {
					"type": "ZString",
					"value": "LThighTwist1"
				},
				"m_mTransform": {
					"type": "SMatrix43",
					"value": {
						"rotation": {
							"x": 0,
							"y": 0.019767044762768395,
							"z": 0
						},
						"position": {
							"x": 0.054471999406814575,
							"y": 0.016683999449014664,
							"z": 0.0043680001981556416
						}
					}
				},
				"m_bCollisionGroup0": {
					"type": "bool",
					"value": true
				}
			},
			"postInitProperties": {
				"m_eidParent": {
					"type": "SEntityTemplateReference",
					"value": "953af237732cbd82"
				}
			},
			"editorOnly": false,
			"platformSpecificPropertyValues": []
		},
		"8bdcca8ce11e0d1b": {
			"parent": "953af237732cbd82",
			"name": "C_TighMid_R",
			"template": "[assembly:/templates/aspectdummy.aspect]([modules:/zclothsphere.class].entitytype,[modules:/zboneattachaspect.class].entitytype).pc_entitytype",
			"blueprint": "[assembly:/templates/aspectdummy.aspect]([modules:/zclothsphere.class].entitytype,[modules:/zboneattachaspect.class].entitytype).pc_entityblueprint",
			"properties": {
				"m_fRadius": {
					"type": "float32",
					"value": 0.10499999672174454
				},
				"m_BoneName": {
					"type": "ZString",
					"value": "RThighTwist1"
				},
				"m_mTransform": {
					"type": "SMatrix43",
					"value": {
						"rotation": {
							"x": 0,
							"y": 0,
							"z": 0
						},
						"position": {
							"x": 0.05400199815630913,
							"y": 0.009704000316560268,
							"z": -0.0026199999265372753
						}
					}
				}
			},
			"postInitProperties": {
				"m_eidParent": {
					"type": "SEntityTemplateReference",
					"value": "953af237732cbd82"
				}
			},
			"editorOnly": false,
			"platformSpecificPropertyValues": []
		},
		"522a36f0dc2418c9": {
			"parent": "953af237732cbd82",
			"name": "CChain_Spine_R",
			"template": "[modules:/zclothspherechain.class].pc_entitytype",
			"blueprint": "[modules:/zclothspherechain.class].pc_entityblueprint",
			"properties": {
				"m_mTransform": {
					"type": "SMatrix43",
					"value": {
						"rotation": {
							"x": 0,
							"y": 0,
							"z": 0
						},
						"position": {
							"x": -1.290655973207322e-07,
							"y": 2.171457902377938e-09,
							"z": 0
						}
					}
				}
			},
			"postInitProperties": {
				"m_Spheres": {
					"type": "TArray<SEntityTemplateReference>",
					"value": ["52f9dc87471a25e6", "e4c89fe00a689348", "c493c3a4adabb790"]
				},
				"m_eidParent": {
					"type": "SEntityTemplateReference",
					"value": "953af237732cbd82"
				}
			},
			"editorOnly": false,
			"platformSpecificPropertyValues": []
		},
		"f80f8602e6256abe": {
			"parent": "953af237732cbd82",
			"name": "ColliderGroup",
			"template": "[modules:/zclothcollidergroup.class].pc_entitytype",
			"blueprint": "[modules:/zclothcollidergroup.class].pc_entityblueprint",
			"properties": {
				"m_ClothColliders": {
					"type": "TArray<SEntityTemplateReference>",
					"value": ["48a1116308a21bcc", "522a36f0dc2418c9", "ba4085bde0d955d3"]
				}
			},
			"postInitProperties": {
				"m_eidParent": {
					"type": "SEntityTemplateReference",
					"value": "953af237732cbd82"
				}
			},
			"editorOnly": false,
			"platformSpecificPropertyValues": []
		},
		"554ce92786b4b570": {
			"parent": "65e0396981b14ff6",
			"name": "TShirt_CrewNeck_Tkd",
			"template": "00315E5B72C1A976",
			"blueprint": "00E85FA3F3B639A8",
			"properties": {
				"Diffuse_Color_01_Value": {
					"type": "SColorRGB",
					"value": "#c28344"
				},
				"ConstantVector1D_03_Value": {
					"type": "float32",
					"value": 0.40000000596046448
				},
				"m_pMeshResource": {
					"type": "ZRuntimeResourceID",
					"value": {
						"resource": "0055543B9E0A9774",
						"flag": "5F"
					}
				},
				"ConstantVector1D_13_Value": {
					"type": "float32",
					"value": 0.039999999105930328
				}
			},
			"postInitProperties": {},
			"editorOnly": false,
			"platformSpecificPropertyValues": []
		},
		"bf93355e48ea16c1": {
			"parent": "65e0396981b14ff6",
			"name": "Socks_Stayup",
			"template": "00F08922DD07B15C",
			"blueprint": "00CDED97BA9FB106",
			"properties": {
				"Diffuse_Color_01_Value": {
					"type": "SColorRGB",
					"value": "#e8e8e8"
				},
				"ConstantVector1D_05_Value": {
					"type": "float32",
					"value": 0.5
				},
				"m_pMeshResource": {
					"type": "ZRuntimeResourceID",
					"value": {
						"resource": "00E19C7870166F8E",
						"flag": "5F"
					}
				}
			},
			"postInitProperties": {},
			"editorOnly": false,
			"platformSpecificPropertyValues": []
		},
		"e3473b2342b29aee": {
			"parent": "953af237732cbd82",
			"name": "C_Knee_R",
			"template": "[assembly:/templates/aspectdummy.aspect]([modules:/zclothsphere.class].entitytype,[modules:/zboneattachaspect.class].entitytype).pc_entitytype",
			"blueprint": "[assembly:/templates/aspectdummy.aspect]([modules:/zclothsphere.class].entitytype,[modules:/zboneattachaspect.class].entitytype).pc_entityblueprint",
			"properties": {
				"m_fRadius": {
					"type": "float32",
					"value": 0.070000000298023224
				},
				"m_BoneName": {
					"type": "ZString",
					"value": "R_Calf"
				},
				"m_mTransform": {
					"type": "SMatrix43",
					"value": {
						"rotation": {
							"x": 0,
							"y": 0,
							"z": 0
						},
						"position": {
							"x": 0.0013312119990587234,
							"y": -0.010140989907085896,
							"z": -0.0023399998899549246
						}
					}
				}
			},
			"postInitProperties": {
				"m_eidParent": {
					"type": "SEntityTemplateReference",
					"value": "953af237732cbd82"
				}
			},
			"editorOnly": false,
			"platformSpecificPropertyValues": []
		},
		"c493c3a4adabb790": {
			"parent": "953af237732cbd82",
			"name": "C_Spine2_R",
			"template": "[assembly:/templates/aspectdummy.aspect]([modules:/zclothsphere.class].entitytype,[modules:/zboneattachaspect.class].entitytype).pc_entitytype",
			"blueprint": "[assembly:/templates/aspectdummy.aspect]([modules:/zclothsphere.class].entitytype,[modules:/zboneattachaspect.class].entitytype).pc_entityblueprint",
			"properties": {
				"m_BoneName": {
					"type": "ZString",
					"value": "Spine2"
				},
				"m_fRadius": {
					"type": "float32",
					"value": 0.15000000596046448
				},
				"m_mTransform": {
					"type": "SMatrix43",
					"value": {
						"rotation": {
							"x": 0.6075190242261483,
							"y": 0.04131026166972855,
							"z": 7.778168579045881
						},
						"position": {
							"x": -0.034866999834775925,
							"y": 0.024687999859452248,
							"z": -0.04030299931764603
						}
					}
				},
				"m_bEnabled": {
					"type": "bool",
					"value": true
				}
			},
			"postInitProperties": {
				"m_eidParent": {
					"type": "SEntityTemplateReference",
					"value": "953af237732cbd82"
				}
			},
			"editorOnly": false,
			"platformSpecificPropertyValues": []
		},
		"953af237732cbd82": {
			"parent": "95fd9e2d66d53952",
			"name": "Collider_Jacket_Suit_Closed",
			"template": "[modules:/zcompositeentity.class].pc_entitytype",
			"blueprint": "[modules:/zcompositeentity.class].pc_entityblueprint",
			"properties": {
				"m_mTransform": {
					"type": "SMatrix43",
					"value": {
						"rotation": {
							"x": 3.58917243279456,
							"y": -1.799259960408176,
							"z": 30.152140421688635
						},
						"position": {
							"x": -0.349572092294693,
							"y": 0.008107620291411877,
							"z": 0.03596305102109909
						}
					}
				},
				"m_eidParent": {
					"type": "SEntityTemplateReference",
					"value": "95fd9e2d66d53952"
				}
			},
			"postInitProperties": {},
			"editorOnly": false,
			"platformSpecificPropertyValues": [],
			"propertyAliases": [{
				"exposeProperty": "m_linkedEntity",
				"onEntity": "5371e11f2ee44b9e",
				"asProperty": "m_linkedEntity"
			}, {
				"exposeProperty": "m_linkedEntity",
				"onEntity": "e3473b2342b29aee",
				"asProperty": "m_linkedEntity"
			}, {
				"exposeProperty": "m_linkedEntity",
				"onEntity": "374a936d9982adb6",
				"asProperty": "m_linkedEntity"
			}, {
				"exposeProperty": "m_linkedEntity",
				"onEntity": "8bdcca8ce11e0d1b",
				"asProperty": "m_linkedEntity"
			}, {
				"exposeProperty": "m_linkedEntity",
				"onEntity": "bb8eaa6fe4d1f2d6",
				"asProperty": "m_linkedEntity"
			}, {
				"exposeProperty": "m_linkedEntity",
				"onEntity": "616f24e83f2dbaec",
				"asProperty": "m_linkedEntity"
			}, {
				"exposeProperty": "m_linkedEntity",
				"onEntity": "bf646f13e07b5c0f",
				"asProperty": "m_linkedEntity"
			}, {
				"exposeProperty": "m_linkedEntity",
				"onEntity": "c493c3a4adabb790",
				"asProperty": "m_linkedEntity"
			}, {
				"exposeProperty": "m_linkedEntity",
				"onEntity": "e4c89fe00a689348",
				"asProperty": "m_linkedEntity"
			}, {
				"exposeProperty": "m_linkedEntity",
				"onEntity": "52f9dc87471a25e6",
				"asProperty": "m_linkedEntity"
			}, {
				"exposeProperty": "m_linkedEntity",
				"onEntity": "34e34008338e1530",
				"asProperty": "m_linkedEntity"
			}, {
				"exposeProperty": "m_linkedEntity",
				"onEntity": "5eea0e4a7d7e8d85",
				"asProperty": "m_linkedEntity"
			}, {
				"exposeProperty": "m_linkedEntity",
				"onEntity": "f3a9fead7a5fcc41",
				"asProperty": "m_linkedEntity"
			}, {
				"exposeProperty": "m_linkedEntity",
				"onEntity": "1114738fa3dc3219",
				"asProperty": "m_linkedEntity"
			}],
			"exposedInterfaces": [
				["ZClothCollider", "f80f8602e6256abe"],
				["ZClothColliderGroup", "f80f8602e6256abe"]
			]
		},
		"5960b240f2cd0b61": {
			"parent": "65e0396981b14ff6",
			"name": "Pants_Dress_Regular_NoBrk_Wet",
			"template": "00DC7FEE9C30417E",
			"blueprint": "00FAB14291BB8CAD",
			"properties": {
				"Diffuse_Color_01_Value": {
					"type": "SColorRGB",
					"value": "#b0b0b0"
				},
				"Diffuse_Saturation_01_Value": {
					"type": "float32",
					"value": 0
				},
				"ConstantVector1D_01_Value": {
					"type": "float32",
					"value": 1.2699999809265137
				},
				"m_pMeshResource": {
					"type": "ZRuntimeResourceID",
					"value": {
						"resource": "009E7EA34D068541",
						"flag": "5F"
					}
				}
			},
			"postInitProperties": {},
			"editorOnly": false,
			"platformSpecificPropertyValues": []
		}
	},
	"propertyOverrides": [],
	"overrideDeletes": [],
	"pinConnectionOverrides": [],
	"pinConnectionOverrideDeletes": [],
	"externalScenes": [],
	"subType": 0,
	"quickEntityVersion": 2.1
}